serpextract/__init__.py
serpextract/search_engines.json
serpextract/serpextract.py
serpextract-0.7.3.dist-info/LICENSE.txt
serpextract-0.7.3.dist-info/METADATA
serpextract-0.7.3.dist-info/WHEEL
serpextract-0.7.3.dist-info/entry_points.txt
serpextract-0.7.3.dist-info/top_level.txt
serpextract-0.7.3.dist-info/RECORD
