Metadata-Version: 2.1
Name: serpextract
Version: 0.7.3
Summary: Easy extraction of keywords from search engine results pages (SERPs).
Home-page: http://github.com/Parsely/serpextract/
Author: Mike Sukmanowsky
Author-email: mike@parsely.com
License: LICENSE.txt
Keywords: search engines keyword extract
Platform: any
Classifier: Development Status :: 3 - Alpha
Classifier: Intended Audience :: Developers
Classifier: Intended Audience :: End Users/Desktop
Classifier: Intended Audience :: Information Technology
Classifier: License :: OSI Approved :: BSD License
Classifier: Operating System :: MacOS
Classifier: Operating System :: Microsoft :: Windows
Classifier: Operating System :: POSIX
Classifier: Programming Language :: Python
Classifier: Topic :: Internet :: WWW/HTTP
Classifier: Topic :: Internet :: WWW/HTTP :: Dynamic Content
Classifier: Topic :: Internet :: WWW/HTTP :: Indexing/Search
Classifier: Topic :: Software Development :: Libraries :: Python Modules
Classifier: Topic :: Utilities
Requires-Dist: iso3166 (>=0.4)
Requires-Dist: pylru (>=1.0.3)
Requires-Dist: tldextract (>=1.2)
Requires-Dist: ruamel.yaml
